LICENSE
setup.py
dbPath/__init__.py
dbPath/database.py
dbPath/test.py
dbPath.egg-info/PKG-INFO
dbPath.egg-info/SOURCES.txt
dbPath.egg-info/dependency_links.txt
dbPath.egg-info/requires.txt
dbPath.egg-info/top_level.txt