Metadata-Version: 2.1
Name: dbPath
Version: 0.1.0
Summary: A database name Getter
Home-page: UNKNOWN
Author: Cai Jianping
Author-email: jpingcai@163.com
License: MIT Licence
Keywords: database,localServer
Platform: any
License-File: LICENSE
